[
        { "paper_title":"Surprised by Joy", "conference":"Mark Batty Publisher", "publish_date":"2020-12-19T23" }, 
        { "paper_title":"Those Barren Leaves, Thrones, Dominations", "conference":"Martinus Nijhoff Publishers", "publish_date":"2021-01-22T23" },
        {"paper_title":"The Other Side of Silence", "conference":"Brimstone Press", "publish_date":"2021-02-19T23" }, 
        { "paper_title":"Mother Night", "conference":"Gefen Publishing House", "publish_date":"2021-01-25T23" }, 
        { "paper_title":"The Grapes of Wrath", "conference":"Chronicle Books", "publish_date":"2020-12-12T23" }, 
        { "paper_title":"Unweaving the Rainbow", "conference":"André Deutsch", "publish_date":"2021-01-20T23" }, 
        { "paper_title":"In a Dry Season", "conference":"Athabasca University Press", "publish_date":"2020-12-24T23" }, 
        { "paper_title":"The Line of Beauty", "conference":"Libertas Academica", "publish_date":"2020-12-06T23" }, 
        { "paper_title":"The Little Foxes", "conference":"Sams Publishing", "publish_date":"2021-02-22T23" }, 
        { "paper_title":"The House of Mirth", "conference":"Virgin Publishing", "publish_date":"2021-02-14T23" }, 
        { "paper_title":"The Glory and the Dream", "conference":"Canongate Books", "publish_date":"2021-01-08T23" }, 
        { "paper_title":"Frequent Hearses", "conference":"Mark Batty Publisher", "publish_date":"2020-12-26T23" }, 
        { "paper_title":"Infinite Jest", "conference":"Basic Books", "publish_date":"2020-12-17T23" }, 
        { "paper_title":"The Other Side of Silence", "conference":"Shambhala Publications", "publish_date":"2021-02-22T23" }, 
        { "paper_title":"Blithe Spirit", "conference":"Booktrope", "publish_date":"2021-02-14T23" }, 
        { "paper_title":"I Will Fear No Evil", "conference":"Bella Books", "publish_date":"2021-02-22T23" }, 
        { "paper_title":"Number the Stars", "conference":"Gefen Publishing House", "publish_date":"2021-02-17T23" }, 
        { "paper_title":"Little Hands Clapping", "conference":"Central European University Press", "publish_date":"2021-01-24T23" }, 
        { "paper_title":"The Mermaids Singing", "conference":"University of Michigan Press", "publish_date":"2021-02-24T23" }, 
        { "paper_title":"To a God Unknown", "conference":"Faber and Faber", "publish_date":"2021-02-23T23" }, 
        { "paper_title":"Noli Me Tangere", "conference":"Edupedia Publications", "publish_date":"2020-11-23T23" }, 
        { "paper_title":"Surprised by Joy", "conference":"Kessinger Publishing", "publish_date":"2020-12-23T23" }, 
        { "paper_title":"Antic Hay", "conference":"Ten Speed Press", "publish_date":"2021-01-30T23" }, 
        { "paper_title":"Absalom, Absalom!", "conference":"Blackstaff Press", "publish_date":"2021-02-09T23" }, 
        { "paper_title":"Recalled to Life", "conference":"Gay Men's Press", "publish_date":"2021-01-29T23" }, 
        { "paper_title":"A Time of Gifts", "conference":"Mascot Books", "publish_date":"2021-02-18T23" }, 
        { "paper_title":"Nectar in a Sieve", "conference":"André Deutsch", "publish_date":"2021-01-13T23" }, 
        { "paper_title":"Recalled to Life", "conference":"University of Michigan Press", "publish_date":"2021-01-06T23" }, 
        { "paper_title":"Such, Such Were the Joys", "conference":"Harry N. Abrams, Inc.", "publish_date":"2021-01-18T23" }, 
        { "paper_title":"Oh! To be in England", "conference":"Matthias Media", "publish_date":"2021-01-03T23" }
    ]